INSTALL
MANIFEST.in
ez_setup.py
release.sh
setup.py
clonedigger/LICENSE.txt
clonedigger/README.txt
clonedigger/__init__.py
clonedigger/abstract_syntax_tree.py
clonedigger/anti_unification.py
clonedigger/arguments.py
clonedigger/ast_suppliers.py
clonedigger/clone_detection_algorithm.py
clonedigger/clonedigger.py
clonedigger/html_report.py
clonedigger/java_antlr.py
clonedigger/python_compiler.py
clonedigger/suffix_tree.py
clonedigger.egg-info/PKG-INFO
clonedigger.egg-info/SOURCES.txt
clonedigger.egg-info/dependency_links.txt
clonedigger.egg-info/entry_points.txt
clonedigger.egg-info/not-zip-safe
clonedigger.egg-info/requires.txt
clonedigger.egg-info/top_level.txt
clonedigger/antlr_runtime/runtime-2008-01-10.16.jar
clonedigger/java_antlr/JavaAST.g
clonedigger/java_antlr/JavaAST.tokens
clonedigger/java_antlr/MyAstNode.java
clonedigger/java_antlr/MyAstNodeAdaptor.java
clonedigger/java_antlr/TreeProducer.jar
clonedigger/java_antlr/TreeProducer.java
clonedigger/java_antlr/build_jar.sh
clonedigger/logilab/__init__.py
clonedigger/logilab/astng/__init__.py
clonedigger/logilab/astng/__pkginfo__.py
clonedigger/logilab/astng/_exceptions.py
clonedigger/logilab/astng/astutils.py
clonedigger/logilab/astng/builder.py
clonedigger/logilab/astng/inference.py
clonedigger/logilab/astng/inspector.py
clonedigger/logilab/astng/lookup.py
clonedigger/logilab/astng/manager.py
clonedigger/logilab/astng/nodes.py
clonedigger/logilab/astng/raw_building.py
clonedigger/logilab/astng/scoped_nodes.py
clonedigger/logilab/astng/utils.py
clonedigger/logilab/common/__init__.py
clonedigger/logilab/common/__pkginfo__.py
clonedigger/logilab/common/adbh.py
clonedigger/logilab/common/astutils.py
clonedigger/logilab/common/bind.py
clonedigger/logilab/common/cache.py
clonedigger/logilab/common/changelog.py
clonedigger/logilab/common/clcommands.py
clonedigger/logilab/common/cli.py
clonedigger/logilab/common/compat.py
clonedigger/logilab/common/configuration.py
clonedigger/logilab/common/corbautils.py
clonedigger/logilab/common/daemon.py
clonedigger/logilab/common/date.py
clonedigger/logilab/common/db.py
clonedigger/logilab/common/debugger.py
clonedigger/logilab/common/decorators.py
clonedigger/logilab/common/deprecation.py
