Metadata-Version: 1.0
Name: clonedigger
Version: 1.0.4-beta
Summary: Clone Digger aimed to detect similar code in Python and Java programs.
Home-page: http://clonedigger.sourceforge.net
Author: Peter Bulychev
Author-email: peter.bulychev@gmail.com
License: GPL
Keywords: buildout buildbot
Platform: UNKNOWN
Classifier: Intended Audience :: Developers
Classifier: Topic :: Software Development :: Libraries :: Python Modules
